sentinel_toolkit/__init__.py
sentinel_toolkit/colorimetry/__init__.py
sentinel_toolkit/colorimetry/illuminants/__init__.py
sentinel_toolkit/colorimetry/illuminants/d65.py
sentinel_toolkit/colorimetry/illuminants/illuminants.py
sentinel_toolkit/colorimetry/illuminants/tests/__init__.py
sentinel_toolkit/colorimetry/illuminants/tests/test_data/D65.1nm
sentinel_toolkit/colorimetry/illuminants/tests/test_illuminants.py
sentinel_toolkit/colorimetry/sentinel_values.py
sentinel_toolkit/colorimetry/tests/__init__.py
sentinel_toolkit/colorimetry/tests/test_sentinel_values.py
sentinel_toolkit/converter/__init__.py
sentinel_toolkit/converter/converter.py
sentinel_toolkit/converter/tests/__init__.py
sentinel_toolkit/converter/tests/test_converter.py
sentinel_toolkit/converter/tests/test_data/s2a_srf.xlsx
sentinel_toolkit/ecostress/__init__.py
sentinel_toolkit/ecostress/ecostress.py
sentinel_toolkit/ecostress/ecostress_db_generator.py
sentinel_toolkit/ecostress/tests/__init__.py
sentinel_toolkit/ecostress/tests/test_ecostress.py
sentinel_toolkit/ecostress/tests/test_ecostress_db_generator.py
sentinel_toolkit/product/__init__.py
sentinel_toolkit/product/product_metadata/__init__.py
sentinel_toolkit/product/product_metadata/s2_metadata.py
sentinel_toolkit/product/product_metadata/tests/__init__.py
sentinel_toolkit/product/product_metadata/tests/test_data/metadata.xml
sentinel_toolkit/product/product_metadata/tests/test_s2metadata.py
sentinel_toolkit/product/s2_product.py
sentinel_toolkit/product/tests/__init__.py
sentinel_toolkit/product/tests/test_data/S2B_MSIL2A_20220915T092029_N0400_R093_T34TGN_20220915T112452.SAFE/GRANULE/L2A_T34TGN_A028862_20220915T092030/IMG_DATA/R10m/T34TGN_20220915T092029_B02_10m.jp2
sentinel_toolkit/product/tests/test_data/S2B_MSIL2A_20220915T092029_N0400_R093_T34TGN_20220915T112452.SAFE/GRANULE/L2A_T34TGN_A028862_20220915T092030/IMG_DATA/R10m/T34TGN_20220915T092029_B03_10m.jp2
sentinel_toolkit-7.0.6.dist-info/LICENSE
sentinel_toolkit-7.0.6.dist-info/METADATA
sentinel_toolkit-7.0.6.dist-info/WHEEL
sentinel_toolkit-7.0.6.dist-info/RECORD
