Metadata-Version: 2.1
Name: sentinel-toolkit
Version: 7.0.6
Summary: Various sentinel tools
Home-page: https://github.com/sentinel-toolkit/sentinel-toolkit
License: Apache-2.0
Keywords: sentinel,satellite,sentinel-2,sentinel-2,sentinel-toolkit
Author: Georgi Genchev
Author-email: gdgenchev97@gmail.com
Maintainer: Georgi Genchev
Maintainer-email: gdgenchev97@gmail.com
Requires-Python: >=3.8,<3.11
Classifier: License :: OSI Approved :: Apache Software License
Classifier: Programming Language :: Python :: 3
Classifier: Programming Language :: Python :: 3.8
Classifier: Programming Language :: Python :: 3.9
Classifier: Programming Language :: Python :: 3.10
Requires-Dist: colour-science (>=0.4.1,<0.5.0)
Requires-Dist: elementpath (>=3.0.2,<5.0.0)
Requires-Dist: openpyxl (>=3.0.10,<4.0.0)
Requires-Dist: pandas (>=1.4.2,<3.0.0)
Requires-Dist: rasterio (>=1.2,<2.0)
Requires-Dist: spectral (>=0.22.4,<0.24.0)
Project-URL: Repository, https://github.com/sentinel-toolkit/sentinel-toolkit
